registrypol/__init__.py
registrypol/policy.py
registrypol/utils.py
registrypol/values.py
registrypol-1.0.1.dist-info/licenses/LICENSE
tests/__init__.py
tests/test_policy.py
tests/test_utils.py
tests/test_values.py
registrypol-1.0.1.dist-info/METADATA
registrypol-1.0.1.dist-info/WHEEL
registrypol-1.0.1.dist-info/top_level.txt
registrypol-1.0.1.dist-info/RECORD
