Metadata-Version: 2.4
Name: registrypol
Version: 1.0.1
Summary: Windows Registry Policy parser and emitter for Python
Home-page: https://github.com/LiamSennitt/registrypol
Author: Liam Sennitt
License-File: LICENSE
Dynamic: author
Dynamic: description
Dynamic: description-content-type
Dynamic: home-page
Dynamic: license-file
Dynamic: summary
